JMeterClasses.py
JMeterLib.py
robotframework_jmeterlibrary_fix-1.0.data/data/Doc/JMeterLib.html
robotframework_jmeterlibrary_fix-1.0.data/data/Scripts/jmeterLibExample.txt
robotframework_jmeterlibrary_fix-1.0.dist-info/METADATA
robotframework_jmeterlibrary_fix-1.0.dist-info/WHEEL
robotframework_jmeterlibrary_fix-1.0.dist-info/top_level.txt
robotframework_jmeterlibrary_fix-1.0.dist-info/RECORD
