Metadata-Version: 2.1
Name: robotframework-jmeterlibrary-fix
Version: 1.0
Summary: Robot Framework JMeter Library
Home-page: https://github.com/pdfff/jmeter_robot_fix
Author: Igor Bushnev
Author-email: arslanjik95@gmail.com
License: LGPLv3
